commandlinestart/__init__.py
commandlinestart/commands.py
commandlinestart/output.py
commandlinestart-0.2.2.dist-info/METADATA
commandlinestart-0.2.2.dist-info/WHEEL
commandlinestart-0.2.2.dist-info/RECORD
